pyproject_version/__init__.py
pyproject_version/cli.py
pyproject_version/tools.py
pyproject_version-0.1.0.dev1.dist-info/LICENSE
pyproject_version-0.1.0.dev1.dist-info/METADATA
pyproject_version-0.1.0.dev1.dist-info/WHEEL
pyproject_version-0.1.0.dev1.dist-info/entry_points.txt
pyproject_version-0.1.0.dev1.dist-info/RECORD
