Metadata-Version: 2.1
Name: pyproject-version
Version: 0.1.0.dev1
Summary: Utilities for maintaining the version in python projects.
License: MIT
Author: Cory Laughlin
Author-email: laughlin.cory@gmail.com
Requires-Python: >=3.11,<3.13
Classifier: License :: OSI Approved :: MIT License
Classifier: Programming Language :: Python :: 3
Classifier: Programming Language :: Python :: 3.11
Requires-Dist: click (>=8.1.7,<9.0.0)
Requires-Dist: semver (>=3.0.2,<4.0.0)
Requires-Dist: tomlkit (>=0.12.4,<0.13.0)
